[
    {
        "ID": "B00008URRV.html",
        "NAME": "Westinghouse WST1551 Wire Deluxe Vacuum with 10-Foot Extension Hose",
        "CATEGORY": [
            "Home & Kitchen",
            "Vacuums & Floor Care",
            "Vacuums",
            "Upright Vacuums"
        ],
        "DESCRIPTION": [
            "Handle instantly converts to hose for above-floor cleaning",
            "Long-life HEPA filter lasts 7 years",
            "Powerful 12-amp, 2-motor system with bagless dirt collection",
            "Rotating brush shuts off for bare floor cleaning",
            "13-1/2-inch cleaning path; 45 inches high"
        ]
    },
    {
        "ID": "B000KIBALA.html",
        "NAME": "Dirt Devil Action Bagless Upright",
        "CATEGORY": [
            "Home & Kitchen",
            "Vacuums & Floor Care",
            "Vacuums",
            "Upright Vacuums"
        ],
        "DESCRIPTION": [
            "New filtration design - no messy interaction with filter",
            "Also includes a Rotating Power Brush tool to quickly clean stairs and upholstery",
            "30' Cord - clean multiple rooms without stopping",
            "Lifetime washable HEPA filter traps 100% of common allergens - Perfect for allergy sufferers and pet owners",
            "Onboard attachments include a ready-to-use hose, extension wand, and crevice tool to clean those hard-to-reach places"
        ]
    },
    {
        "ID": "B000N1XPJ4.html",
        "NAME": "Dirt Devil M120000 Spinnergy Upright Vacuum Cleaner",
        "CATEGORY": [
            "Home & Kitchen",
            "Vacuums & Floor Care",
            "Vacuums",
            "Upright Vacuums"
        ],
        "DESCRIPTION": [
            "Multi-stage cyclonic technology provides long-lasting suction power",
            "Removable handle converts into long-reaching extension wand",
            "Clean-release dirt cup; HEPA filter; adjustable height; 30-foot cord",
            "Upright vacuum cleaner with on-board tools and rotating power brush",
            "Measures approximately 15 by 12 by 44 inches; 3-year warranty"
        ]
    },
    {
        "ID": "B000PC8FW8.html",
        "NAME": "iRobot 5942 Scooba Replenish Kit",
        "CATEGORY": [
            "Home & Kitchen",
            "Vacuums & Floor Care",
            "Vacuums"
        ],
        "DESCRIPTION": [
            "Cleaning head assembly is easy to clean",
            "Keeps Scooba running at peak performance"
        ]
    },
    {
        "ID": "B00006IIV7.html",
        "NAME": "Hoover U5347900 WidePath Bagless Upright Vacuum",
        "CATEGORY": [
            "Home & Kitchen",
            "Vacuums & Floor Care",
            "Vacuums",
            "Upright Vacuums"
        ],
        "DESCRIPTION": [
            "Measures 15 by 13 by 43 inches",
            "Extra-powerful tool suction",
            "Lightest bagless upright made by Hoover",
            "Traps 100 percent of dust mites and 99.98 percent of ragweed and grass pollen",
            "Wide cleaning path design for efficient floor coverage"
        ]
    },
    {
        "ID": "B0000UJH5E.html",
        "NAME": "Eureka 3684D TheBOSS Mighty Mite",
        "CATEGORY": [
            "Home & Kitchen",
            "Vacuums & Floor Care",
            "Vacuums",
            "Canister Vacuums"
        ],
        "DESCRIPTION": [
            "12 amps",
            "15-inch cleaning path",
            "Includes stretch hose, tools-on-board, and headlight"
        ]
    },
    {
        "ID": "B0000SWDR0.html",
        "NAME": "Eureka EL6989A Electrolux Oxygen Ultra Canister Vacuum Cleaner",
        "CATEGORY": [
            "Home & Kitchen",
            "Vacuums & Floor Care",
            "Vacuums",
            "Canister Vacuums"
        ],
        "DESCRIPTION": [
            "Electronic dust bag indicator tells you when the bag is full",
            "Deluxe bare floor brush included for gently cleaning wood and tile",
            "Powerful 1400 watt variable speed motor",
            "Convenient on-board tool caddy system for cleaning surfaces above the floor (tools included)",
            "Quick-release wand system with fingertip controls lets you switch between floor/specialty"
        ]
    },
    {
        "ID": "B00006IIV3.html",
        "NAME": "Hoover U5435-900 WindTunnel Plus",
        "CATEGORY": [
            "Home & Kitchen",
            "Vacuums & Floor Care",
            "Vacuums",
            "Upright Vacuums"
        ],
        "DESCRIPTION": [
            "Allergen filtration",
            "On-board stretch hose, extension wands, and cleaning tools",
            "Dual brush agitator",
            "Easy access bag hatch",
            "Measures 13 by 12-1/2 by 42-1/2 inches"
        ]
    },
    {
        "ID": "B000HQBTF2.html",
        "NAME": "Bissell PowerForce Bagless Upright Vacuum Cleaner, 65792",
        "CATEGORY": [
            "Home & Kitchen",
            "Vacuums & Floor Care",
            "Vacuums",
            "Upright Vacuums"
        ],
        "DESCRIPTION": [
            "Convenient washable filters make it less expensive to operate",
            "On-board tools",
            "12 amps of power-Bagless technology provides high suction power for thorough cleaning",
            "3-stage filtration system captures dust and micro particles",
            "Lightweight Design is easy to carry and maneuver"
        ]
    },
    {
        "ID": "B0001WW2FS.html",
        "NAME": "Bissell Lift-Off Replacement Belt, 2 pk, 3200",
        "CATEGORY": [
            "Home & Kitchen",
            "Vacuums & Floor Care",
            "Vacuum Parts & Accessories"
        ],
        "DESCRIPTION": [
            "Includes 2 belts",
            "Fits all Lift-Off Bagless Models",
            "Works with Model #s: 18Z6, 37604, 42209, 6860H, 37606, 89Q9, 6850",
            "When do I replace the belt? If the vacuum is not cleaning as well as it had before or the brush roll has stopped turning, you may have to change the belt. To change the belt, please refer to your models user guide for installation instructions."
        ]
    },
    {
        "ID": "B0009EY0PS.html",
        "NAME": "BLACK+DECKER S600 Cordless Powered Scrubber",
        "CATEGORY": [
            "Home & Kitchen",
            "Vacuums & Floor Care",
            "Vacuums",
            "Handheld Vacuums"
        ],
        "DESCRIPTION": [
            "Powerful scrubber for kitchen, bathroom and outdoor cleaning",
            "On Board Cleaning System allows you to use any liquid based cleaner to spray and go!",
            "Flexible head attachment allows tool to curb to any surface",
            "Fully submersible",
            "Convenient storage caddy holds tool and all 9 accessories"
        ]
    },
    {
        "ID": "B0000AFQJ3.html",
        "NAME": "Eureka 4880BT Whirlwind Upright True HEPA Bagless Cyclonic Vacuum",
        "CATEGORY": [
            "Home & Kitchen",
            "Vacuums & Floor Care",
            "Vacuums",
            "Upright Vacuums"
        ],
        "DESCRIPTION": [
            "15 by 13-1/2 by 44-1/2 inches; 30-foot power cord",
            "True HEPA filtration traps 100 percent of common allergens",
            "Suitable for carpet, hard floors, and upholstery",
            "15-inch cleaning path; 11-foot cleaning reach above ground",
            "Bagless cyclonic suction with large transparent dust cup"
        ]
    },
    {
        "ID": "B000IZDUJU.html",
        "NAME": "Remanufactured iRobot Scooba Floor Washing Robotic Hard Surface Cleaner, Assorted Colors",
        "CATEGORY": [
            "Home & Kitchen",
            "Vacuums & Floor Care",
            "Vacuums",
            "Robotic Vacuums"
        ],
        "DESCRIPTION": [
            "Simple to operate--fill tank, press \"Clean,\" and empty tank when finished",
            "Cleans under furniture, tables, and hard-to-reach places",
            "Model number (5800 or 5999) and color may vary; 90 day limited warranty",
            "Remanufactured floor-washing robot that preps, washes, scrubs, and dries in one pass",
            "Safe to use on most hard floors, including sealed hardwood, linoleum, tile, and marble"
        ]
    },
    {
        "ID": "B001I9024G.html",
        "NAME": "iRobot Roomba Pet Series 532 Vacuum Cleaning Robot",
        "CATEGORY": [
            "Home & Kitchen",
            "Vacuums & Floor Care",
            "Vacuums",
            "Robotic Vacuums"
        ],
        "DESCRIPTION": [
            "High capacity sweeper bin for trapping even more pet hair, kitty litter or dander",
            "Cleans up to three standard-sized rooms on a single charge",
            "Ships in Certified Frustration-Free Packaging",
            "Vacuuming robot designed especially for pet owners; comes with extra set of easy-to-clean brushes",
            "2 Virtual Walls tell Roomba where to clean by restricting off-limit areas"
        ]
    },
    {
        "ID": "B000GF57DY.html",
        "NAME": "iRobot Roomba Silver",
        "CATEGORY": [
            "Home & Kitchen",
            "Vacuums & Floor Care",
            "Vacuums",
            "Robotic Vacuums"
        ],
        "DESCRIPTION": [
            "Dirt Detect\u00bf: Roomba actually detects dirty areas and stays cleaning until the dirt is gone",
            "Max mode-use max mode to clean multiple rooms in a single cleaning cycly",
            "Bagless bin-no bags to replace; roomba's bagless bin is easy to empty and holds more dirt than ever",
            "Dirt detect: roomba actually detects dirty areas and stays cleaning until the dirt is gone",
            "Patented cleaning system-roomba' powerful vacuum and counter rotating brushes reach deep into your carpet to remove dirt, dust and pet hair"
        ]
    },
    {
        "ID": "B000246E3G.html",
        "NAME": "Euro-Pro Shark Roadster Canister Vacuum",
        "CATEGORY": [
            "Home & Kitchen",
            "Vacuums & Floor Care",
            "Vacuums",
            "Canister Vacuums"
        ],
        "DESCRIPTION": [
            "Full bag indicator; retractable cord; adjustable suction",
            "Lightweight canister vacuum for low carpets and bare floors",
            "Includes onboard tools for accessory cleaning",
            "1-year warranty",
            "Large wheels for easy mobility"
        ]
    },
    {
        "ID": "B00009R66D.html",
        "NAME": "Hoover U5361-900 Widepath Bagless WindTunnel Upright Vacuum",
        "CATEGORY": [
            "Home & Kitchen",
            "Vacuums & Floor Care",
            "Vacuums",
            "Upright Vacuums"
        ],
        "DESCRIPTION": [
            "Allergen filtration system traps dust mites, ragweed, common pollens",
            "Easy-to-empty dust cup eliminates need for bags",
            "12-amp motor; patented WindTunnel technology enhances cleaning performance",
            "Deluxe stretch hose; two extension wands; four tools; 1-year warranty",
            "Dual edge groomers; 15-inch cleaning path"
        ]
    },
    {
        "ID": "B000SSSQKA.html",
        "NAME": "Panasonic MC-CG467 Multi-Surface Lightweight Canister Vacuum Cleaner, Light Blue",
        "CATEGORY": [
            "Home & Kitchen",
            "Vacuums & Floor Care",
            "Vacuums",
            "Canister Vacuums"
        ],
        "DESCRIPTION": [
            "3-in-1 multi-surface brush for cleaning all floor surfaces",
            "Measures 18-2/7 by 13-4/5 by 12-4/5 inches; 1-year limited warranty",
            "HEPA exhaust filter; on-board crevice tool and dusting brush",
            "360-degree swivel hose; telescopic wand; 2 carry handles",
            "Canister vacuum cleaner with a powerful 11 amp motor"
        ]
    },
    {
        "ID": "B000069BFA.html",
        "NAME": "Euro-Pro Shark EP76 Compact Bagless Canister Vacuum",
        "CATEGORY": [
            "Home & Kitchen",
            "Vacuums & Floor Care",
            "Vacuums",
            "Canister Vacuums"
        ],
        "DESCRIPTION": [
            "Stores vertically or flat, with tubes and floor nozzle locked either way",
            "Extension tubes and 10-1/2-inch-wide nozzle for bare floors and carpets",
            "14 by 9 by 9 inches; 1200 watts; 10 pounds; automatic cord rewind",
            "Compact, powerful, lightweight, portable, bagless canister vacuum",
            "Carries with shoulder strap for furniture, drapes, and lamp shades"
        ]
    },
    {
        "ID": "B0002HBT4W.html",
        "NAME": "Hoover U8125-900 Savvy Dual V Bagged Upright Vacuum",
        "CATEGORY": [
            "Home & Kitchen",
            "Vacuums & Floor Care",
            "Vacuum Parts & Accessories",
            "Bags",
            "Upright Bags"
        ],
        "DESCRIPTION": [
            "SurePass cleaning combines WindTunnel technology, dual agitators, and 2 air paths",
            "Measures 43 by 15-1/8 by 14-1/16 inches; 1-year warranty",
            "Bagged upright vacuum cleaner with carpet-height adjustment and special-edge groomers",
            "No belts to break or replace; custom-control switch; low-profile hood; auto shut-off",
            "On-board attachments and powered hand tool for cleaning stairs and upholstery included"
        ]
    },
    {
        "ID": "B000NW461O.html",
        "NAME": "Eureka The Boss Cordless Rechargeable Handheld Vacuum Cleaner, 79B",
        "CATEGORY": [
            "Home & Kitchen",
            "Vacuums & Floor Care",
            "Vacuums",
            "Handheld Vacuums"
        ],
        "DESCRIPTION": [
            "Clean Air System helps protect the motor; on-board crevice tool",
            "Fingertip on/off control switch; wall-mountable charging base included",
            "Measures approximately 17 by 5 by 4 inches; 1-year limited warranty",
            "Easy-to-empty dustbin; 2-1/2-inch-wide cleaning path; lightweight design",
            "Cordless handheld vacuum cleaner with 3-3/5 volts of rechargeable power"
        ]
    },
    {
        "ID": "B0011MKW6I.html",
        "NAME": "iRobot Roomba 510 Vacuuming Robot",
        "CATEGORY": [
            "Home & Kitchen",
            "Vacuums & Floor Care",
            "Vacuums",
            "Robotic Vacuums"
        ],
        "DESCRIPTION": [
            "Easy-to-empty bagless dustbin; fine-filtration system traps allergens",
            "Vacuuming robot picks up dirt and debris with the touch of a button",
            "Anti-tangle technology; gentle-touch bumper system; built-in cliff sensors",
            "1 Virtual Wall, extra filter, and more included",
            "Measures 16-3/4 by 21 by 5 inches; 1-year limited warranty"
        ]
    },
    {
        "ID": "B001F08WAO.html",
        "NAME": "Readivac 36010 Tiny Turbo 1000-Watt Canister Vacuum, Red - Corded",
        "CATEGORY": [
            "Home & Kitchen",
            "Vacuums & Floor Care",
            "Vacuums",
            "Canister Vacuums"
        ],
        "DESCRIPTION": [
            "1000-Watt motor",
            "Dual function brush head is ideal for carpets and hard surfaces. Foot pedal on the brush head quickly adjusts height of sucton",
            "Lifetime bag replacement",
            "Roll or carry; Light weight only 7-pound easy to carry or roll from room to room with a 25-foot cord",
            "On board accessories include dusting brush, crevice tool, replacement bags, upholstery brush, dual function brush head, extension wands and cord management system"
        ]
    },
    {
        "ID": "B0000DF0R4.html",
        "NAME": "CleanFast OC-910 Handheld Mini-Vac",
        "CATEGORY": [
            "Home & Kitchen",
            "Vacuums & Floor Care",
            "Vacuums",
            "Handheld Vacuums"
        ],
        "DESCRIPTION": [
            "Powerful 600-watt handheld vacuum cleaner in black and silver",
            "10 by 6 by 7 inches; one-year warranty",
            "2 foot flexible hose, dusting brush, crevice tool, shoulder strap",
            "Lightweight, with ergonomic carrying handle and handy shoulder",
            "Built to meet U.S. voltage requirements. Certified, safety-tested, and warrantied for use only in the U.S.",
            "Bagless dirt cup with washable filter and 14-1/2-foot power cord"
        ]
    },
    {
        "ID": "B000ASDV5I.html",
        "NAME": "Bissell 37601 Lift-Off Revolution Turbo Upright Bagless Vacuum",
        "CATEGORY": [
            "Home & Kitchen",
            "Vacuums & Floor Care",
            "Vacuums",
            "Upright Vacuums"
        ],
        "DESCRIPTION": [
            "Bagless upright vacuum with 15-inch clearing path; from industry leader Bissell",
            "Vacuum's sealed HEPA filtration removes up to 99 percent of air impurities and allergens; removable dust cup",
            "Vacuum measures 15 by 13-3/4 by 44 inches and weighs 27.9 pounds upon shipping; limited 1-year warranty",
            "Onboard accessories include handheld Turbo Brush for pet hair extraction and vertical cleaning; 30-foot power cord",
            "12-amp motor extracts dirt with turbo-powered suction; 7 height settings for different carpet and floor types"
        ]
    },
    {
        "ID": "B000BY9A3I.html",
        "NAME": "Dirt Devil 082700 Vision Turbo Canister Vacuum",
        "CATEGORY": [
            "Home & Kitchen",
            "Vacuums & Floor Care",
            "Vacuums",
            "Canister Vacuums"
        ],
        "DESCRIPTION": [
            "Weighs 11-1/2 pounds; backed by 2 year warranty (parts and motor)",
            "31-inch telescoping metal wand extends to 42-1/2 inches; 20-foot cord with auto rewind",
            "A bagless canister vacuum is great for homes with variety of surfaces and pets",
            "Tools include upholstery tool, crevice tool dusting brush, turbo power hand brush (great for pet hair), floor nozzle, and carpet nozzle",
            "12 amp motor; HEPA filter traps 99.9 percent of dust and allergens"
        ]
    },
    {
        "ID": "B001IF5XF8.html",
        "NAME": "Euro-Pro SV769 Shark 16-4/5-Volt Cordless Handheld Vacuum Cleaner",
        "CATEGORY": [
            "Home & Kitchen",
            "Vacuums & Floor Care",
            "Vacuums",
            "Handheld Vacuums"
        ],
        "DESCRIPTION": [
            "Crevice tool; washable filter; dust cup; charging stand with LED indicator",
            "16-4/5-volt rechargeable, cordless, handheld vacuum cleaner",
            "Twister Cyclonic technology for long-lasting suction power",
            "Detachable motorized brush removes pet hair and dirt from upholstery and carpet",
            "Measures approximately 15 by 4 by 6 inches; 1-year limited warranty"
        ]
    },
    {
        "ID": "B0009K5NBW.html",
        "NAME": "Shark EP187 Retractor Clean Air Cyclonic Power Vac",
        "CATEGORY": [
            "Home & Kitchen",
            "Vacuums & Floor Care",
            "Vacuums",
            "Handheld Vacuums"
        ],
        "DESCRIPTION": [
            "Clean Air Design TapClean Rinseable HEPA filter traps 99.97% of air impurities as small as 0.3 microns, allowing only clean air to be released into your breathable air",
            "No cord to mess with! Equipped with the Retractor retractable power cord",
            "Includes a Large Turbo Brush, great for deep cleaning carpets and stairs",
            "Bagless cup design means no replacement bags required",
            "850 watts of power gives you a powerful vac in a compact convenient package"
        ]
    },
    {
        "ID": "B00022HZ0O.html",
        "NAME": "iRobot Roomba 4900 Self-Charging Drive-On Home Base",
        "CATEGORY": [
            "Home & Kitchen",
            "Vacuums & Floor Care",
            "Vacuums",
            "Robotic Vacuums"
        ],
        "DESCRIPTION": [
            "Fast-charging power supply; APS Fast Charge included",
            "2 convenient lights indicate power and charge function",
            "Measures approximately 13 by 4 inches",
            "Recharges a Roomba APS battery in less than 3 hours",
            "Accessory to Roomba Discovery Series models of floorvacs"
        ]
    },
    {
        "ID": "B000M6MCVW.html",
        "NAME": "Royal Appliance Dirt Devil 0802 Scorpion Handi Stick Convertible Stick/Handheld Vacuum Cleaner",
        "CATEGORY": [
            "Home & Kitchen",
            "Vacuums & Floor Care",
            "Vacuums",
            "Stick Vacuums & Electric Brooms"
        ],
        "DESCRIPTION": [
            "Powerful 9-3/5-volt motor; standard filtration; easy-to-empty dirt cup",
            "Lightweight design; low-profile nozzle; 25-foot cord with cord hook",
            "On-board Quick Flip crevice tool for cleaning hard-to-reach areas",
            "Measures approximately 5-1/2 by 9-1/4 by 40 inches; 1-year limited warranty",
            "Upright stick vacuum cleaner converts to cordless handheld vac"
        ]
    },
    {
        "ID": "B00008URRB.html",
        "NAME": "Bissell 3107B Catch-All Vac",
        "CATEGORY": [
            "Home & Kitchen",
            "Vacuums & Floor Care",
            "Vacuums",
            "Upright Vacuums"
        ],
        "DESCRIPTION": [
            "Electrostatic dry cloth picks up remaining dirt and dust",
            "10 by 8-1/4 by 46 inches; weighs 3.66 pounds",
            "Cordless operation with a 15-minute battery run time",
            "Motorized, non-scratching, rotating brushes pick up large debris",
            "Adjustable handle, easy-empty filter, and non-marring felt-coated wheels"
        ]
    },
    {
        "ID": "B001ICJKNC.html",
        "NAME": "Bissell 2149131 BARE FLOOR TOOL by Bissell",
        "CATEGORY": [
            "Home & Kitchen",
            "Vacuums & Floor Care",
            "Vacuum Parts & Accessories"
        ],
        "DESCRIPTION": [
            "Works with the following models: Bissell 1699X, Bissell 7901 Series, Bissell 7920, Bissell 7950, Bissell 8910 Series",
            "BARE FLOOR ATTACHMENT"
        ]
    },
    {
        "ID": "B000FG0GE4.html",
        "NAME": "Pet Lover Upright Bagless Vacuum 12-amp",
        "CATEGORY": [
            "Home & Kitchen",
            "Vacuums & Floor Care",
            "Vacuums",
            "Upright Vacuums"
        ],
        "DESCRIPTION": [
            "Upright - BAGLESS",
            "Uses Style U Extended Life Belt #61120B, HEPA Filter Cartridge, Style HF7.",
            "Brand:\"PET LOVER\"",
            "Filtration reduces allergens and pet dander.",
            "Pet Power Paw removes pet hair from carpet and upholstery."
        ]
    },
    {
        "ID": "B00008UI0Q.html",
        "NAME": "Hoover U6616-900 WindTunnel Self Propelled Bagless Upright",
        "CATEGORY": [
            "Home & Kitchen",
            "Vacuums & Floor Care",
            "Vacuums",
            "Upright Vacuums"
        ],
        "DESCRIPTION": [
            "WindTunnel technology provides exceptional cleaning",
            "Enhanced twin-chamber bagless system has \u201cNo Touch\u201d filter cleaning",
            "HEPA filter traps more than 99% of dust mites, ragweed, and grass pollen",
            "Onboard power hand tool cleans carpeted stairs and upholstery",
            "Self-propelled vacuum maneuvers nearly effortlessly"
        ]
    },
    {
        "ID": "B00020LFZW.html",
        "NAME": "DeLonghi EB1100 Super Scoopa Lightweight Upright Vacuum",
        "CATEGORY": [
            "Home & Kitchen",
            "Vacuums & Floor Care",
            "Vacuums",
            "Upright Vacuums"
        ],
        "DESCRIPTION": [
            "Electronic indicator light signals when dust bag is full",
            "Folding handle for easy portability",
            "Re-usable double layer dust bag",
            "Wrap-around cord storage",
            "Multi-stage filtering system with carbon-activated filter traps 99.9% of airborne dust and allergens and eliminates unpleasant odors."
        ]
    },
    {
        "ID": "B00008J4C9.html",
        "NAME": "Shark SV745 14-2/5-Volt Cordless Wet/Dry Handheld Vacuum Cleaner",
        "CATEGORY": [
            "Tools & Home Improvement",
            "Power & Hand Tools",
            "Power Tools",
            "Wet-Dry Vacuums"
        ],
        "DESCRIPTION": [
            "Dust cup means no replacement bags to buy; washable filter",
            "Crevice tool, squeegee nozzle, dusting brush, and extension hose included",
            "Cordless handheld vacuum cleaner for cleaning wet or dry spills",
            "Measures approximately 11 by 4 by 6 inches; 1-year limited warranty",
            "LED charging light and low-battery indicator; storage/recharging stand"
        ]
    },
    {
        "ID": "B0000DASBI.html",
        "NAME": "Hoover Flair Bagless Stick Vacuum, Bagless, S2200",
        "CATEGORY": [
            "Home & Kitchen",
            "Vacuums & Floor Care",
            "Vacuums",
            "Stick Vacuums & Electric Brooms"
        ],
        "DESCRIPTION": [
            "Large rear wheels and swivel nozzle for maneuverability",
            "Bagless stick cleaner for bare floors and low carpets",
            "Pop-off dirt cup; multi-stage filtration system",
            "20-foot power cord; quick-release cord hooks; hang up slot",
            "Includes a full 1-year warranty"
        ]
    },
    {
        "ID": "B000069BFD.html",
        "NAME": "Fantom FM760 Twister 500DX Upright Vacuum",
        "CATEGORY": [
            "Home & Kitchen",
            "Vacuums & Floor Care",
            "Vacuums",
            "Upright Vacuums"
        ],
        "DESCRIPTION": [
            "HEPA filter removes 99.97 percent of particles down to 0.3 microns",
            "Moves easily from carpets to hard surfaces",
            "12-amp motor and 12-inch cleaning path",
            "Quick-release dust canister",
            "Measures 13 by 13 by 46 inches"
        ]
    },
    {
        "ID": "B0009SU03K.html",
        "NAME": "Bissell 35951 CleanView Revolution Plus Upright Bagless Vacuum",
        "CATEGORY": [
            "Home & Kitchen",
            "Vacuums & Floor Care",
            "Vacuums"
        ],
        "DESCRIPTION": [
            "Includes dusting brush/upholstery tool, crevice tool, extension wand, Turbo Brush, and extra HEPA filter",
            "Powerful 12-amp motor; dual-edge cleaning with extra-wide cleaning path",
            "HEPA media filter captures more than 99.9% of dust mites, pollen, and ragweed; indicator lets you know when it's time to clean filters",
            "Measures 15 by 12-1/2 by 44 inches; limited 1-year warranty",
            "Bagless upright vacuum offers consistent suction and impressive cleaning performance"
        ]
    },
    {
        "ID": "B001JKKEC4.html",
        "NAME": "Infinuvo CleanMate QQ-2 L Robotic Vacuum Cleaner with Home Charging Base & LCD Display - White",
        "CATEGORY": [
            "Home & Kitchen",
            "Vacuums & Floor Care",
            "Vacuums",
            "Robotic Vacuums"
        ],
        "DESCRIPTION": [
            "Auto-off feature conserves power when unit is not in use and being recharging",
            "Five-step repetitive rotation movement provides the most effective way to clean your rooms",
            "Three washable filters to reduce cost of ownership",
            "Automatically returns to dock for self-recharging when low on battery power",
            "Photo sensor detects stairs to avoid falling down"
        ]
    },
    {
        "ID": "B0000DASBT.html",
        "NAME": "Hoover U5752-900 Bagless WindTunnel Upright Vacuum",
        "CATEGORY": [
            "Home & Kitchen",
            "Vacuums & Floor Care",
            "Vacuums",
            "Upright Vacuums"
        ],
        "DESCRIPTION": [
            "12-amp full-house vacuum with powerful WindTunnel suction",
            "HEPA filter for allergen relief; taps clean and lasts 3 years",
            "Includes powered hand tool, extension wands, dusting brush, and crevice tool",
            "Cleaning path is 15 inches wide",
            "Bagless dirt collection in twin chamber cup with multi-filter system"
        ]
    },
    {
        "ID": "B000U69C44.html",
        "NAME": "Dirt Devil MBV2030SEA Rechargeable Broom Vacuum, Sea Breeze Blue",
        "CATEGORY": [
            "Home & Kitchen",
            "Vacuums & Floor Care",
            "Vacuums"
        ],
        "DESCRIPTION": [
            "Includes snap-off clear dirt canister, 10-inch cleaning nozzle, replaceable filter, and power adaptor; quick no-tool assembly",
            "Replaces broom, dustpan, and vacuum; 60% more powerful than the original Dirt Devil broom vacuum",
            "Lightweight cordless and bagless vacuum for cleaning hard-surface floors",
            "Measures 21 by 13 by 1-1/2 inches; weighs 3-1/2 pounds; 1-year warranty",
            "Powerful 9.6-volt rechargeable battery; foot-activated on/off switch for maximum ease of use"
        ]
    },
    {
        "ID": "B00061W3SA.html",
        "NAME": "Eureka 5550A Maxima Upright Bagless Vacuum",
        "CATEGORY": [
            "Home & Kitchen",
            "Vacuums & Floor Care",
            "Vacuums",
            "Upright Vacuums"
        ],
        "DESCRIPTION": [
            "Measures 15 by 11 by 44 inches; 1-year warranty",
            "3:1 stretch hose extends to 3 times original length for maximum reach",
            "Bagless cyclonic system with HEPA filter and easy-to-empty dust cup",
            "Attachments include dusting brush, upholstery nozzle, and crevice tool",
            "12 amp upright vacuum cleaner provides wide cleaning path"
        ]
    },
    {
        "ID": "B001AR3OPU.html",
        "NAME": "Bissell Momentum Upright Vacuum, Bagless, 82G71",
        "CATEGORY": [
            "Home & Kitchen",
            "Vacuums & Floor Care",
            "Vacuums"
        ],
        "DESCRIPTION": [
            "Includes crevice tool, dusting brush/upholstery tool, TurboBrush, and extension wand",
            "12 amps; includes 30-foot power cord",
            "Powerful suction with exclusive DirtLifter brush system",
            "High-efficiency cyclonic vacuum for superior performance",
            "10.2 x 15.2 x 32.2 inches; 23.2 pounds; 1-year warranty"
        ]
    },
    {
        "ID": "B0009VIFQQ.html",
        "NAME": "Hoover Savvy U8174-900 Bagless Upright Vacuum",
        "CATEGORY": [
            "Home & Kitchen",
            "Vacuums & Floor Care",
            "Vacuums",
            "Upright Vacuums"
        ],
        "DESCRIPTION": [
            "SurePass cleaning system combines WindTunnel technology and 2 air paths",
            "Bagless upright vacuum cleaner for carpets and bare-floor surfaces",
            "HEPA filter removes pollens and allergens; powered hand tool with rotating brush",
            "Measures approximately 20 by 15 by 45 inches; 1-year warranty",
            "Embedded DirtFinder; 15-inch cleaning width; on-board tools; low-profile hood design"
        ]
    },
    {
        "ID": "B00009PGO5.html",
        "NAME": "iRobot Roomba Virtual Wall, 2003",
        "CATEGORY": [
            "Home & Kitchen",
            "Vacuums & Floor Care",
            "Vacuums",
            "Robotic Vacuums"
        ],
        "DESCRIPTION": [
            "Closes off More than One Opening at a time.",
            "For use with iRobot Roomba Intelligent Floorvac Robotic Vacuum, 2100"
        ]
    },
    {
        "ID": "B00188ALYS.html",
        "NAME": "SEBO 9807AM Felix 1 Premium Onyx Upright Vacuum with Parquet, Black/Silver - Corded",
        "CATEGORY": [
            "Industrial & Scientific",
            "Janitorial & Sanitation Supplies",
            "Vacuums & Floor Cleaning Machines",
            "Vacuums",
            "Upright Vacuums"
        ],
        "DESCRIPTION": [
            "Variable suction control on handle with soft start",
            "Easy brush removal and cleaning",
            "A flat-to-the-floor 6-inch profile",
            "Instant-use suction hose, just pull it out to clean corners, crevices or furniture",
            "Detachable suction unit creates a hand-held portable vacuum"
        ]
    },
    {
        "ID": "B00006IIV6.html",
        "NAME": "Hoover U8140-900 WindTunnel VS Bagless Upright Vacuum with Powered Hand Tool, Green",
        "CATEGORY": [
            "Home & Kitchen",
            "Vacuums & Floor Care",
            "Vacuums",
            "Upright Vacuums"
        ],
        "DESCRIPTION": [
            "Includes 1-year limited warranty",
            "Powered hand tool for upholstery and above-floor jobs",
            "Bagless dirt collection",
            "Delivers powerful, edge-to-edge cleaning on carpet and bare floors",
            "Soft, non-marring wheels; measures 15 by 14-1/2 by 43-1/2 inches"
        ]
    },
    {
        "ID": "B000AAJVC8.html",
        "NAME": "Oreck Super-Deluxe Compact Canister Vacuum Cleaner",
        "CATEGORY": [
            "Home & Kitchen",
            "Vacuums & Floor Care",
            "Vacuums",
            "Canister Vacuums"
        ],
        "DESCRIPTION": [
            "Uses Oreck sanitary hypo-allergenic disposable dust bags. Not a dust cup.",
            "The perfect vacuum cleaner for hard-to-reach places like high ceilings, blinds, mantels and recessed lighting. You can carry it, or wear it over your shoulder.",
            "Strong enough to pick up a 16-lb. Bowling Ball.\u2122",
            "Comes with a complete set of attachments designed to clean everything from computers to chandeliers."
        ]
    },
    {
        "ID": "B000I5Q1IC.html",
        "NAME": "Dyson DC16 Root 6 Handheld Vacuum Cleaner",
        "CATEGORY": [
            "Home & Kitchen",
            "Vacuums & Floor Care",
            "Vacuums",
            "Handheld Vacuums"
        ],
        "DESCRIPTION": [
            "Measures 4-2/7 by 18-2/7 by 8-8/9 inches; 2-year warranty",
            "Battery charger, crevice tool, and combination accessory tool included",
            "Twice the suction of other handhelds; recharges 3 times faster",
            "Bagless handheld vacuum cleaner with Root Cyclone technology",
            "Cordless; picks up large debris; 1-touch cup-emptying system"
        ]
    },
    {
        "ID": "B00007IP3O.html",
        "NAME": "Eureka 5843AZ Litespeed Upright Vacuum",
        "CATEGORY": [
            "Home & Kitchen",
            "Vacuums & Floor Care",
            "Vacuums",
            "Upright Vacuums"
        ],
        "DESCRIPTION": [
            "True HEPA filtration traps 99.97 percent of allergens and irritants",
            "Wide 15-inch cleaning path for efficient floor coverage",
            "Includes self-cleaning electrostatic Spin Duster for delicate surfaces",
            "Cyclonic dirt collection eliminates need for bags",
            "Ultra-light structure weighs only 18 pounds"
        ]
    },
    {
        "ID": "B0009HALDK.html",
        "NAME": "Hoover Factory-Reconditioned U6600-9RM WindTunnel Self-Propelled Bagless Upright Vacuum",
        "CATEGORY": [
            "Home & Kitchen",
            "Vacuums & Floor Care",
            "Vacuums",
            "Upright Vacuums"
        ],
        "DESCRIPTION": [
            "Patented WindTunnel Technology",
            "Onboard tools, hose, Dusting brush, furniture nozzle, wands & crevice wand.",
            "31 ft. cord; 15 inch cleaning path",
            "Factory-Reconditioned to like-new condition; Includes 6 Month Warranty",
            "Brush edge grooming on both sides"
        ]
    },
    {
        "ID": "B0002XYEWU.html",
        "NAME": "Euro-Pro Shark 13-Inch cleaning path 3-Speed Cordless Sweeper",
        "CATEGORY": [
            "Home & Kitchen",
            "Vacuums & Floor Care",
            "Sweepers & Accessories"
        ],
        "DESCRIPTION": [
            "Powerful brush roll; large-capacity removable dust tray; swivel-head design",
            "Wall Hugging Technology-powered side brush gets into corners and grabs dirt along walls",
            "Measures 14-8/9 by 5-1/3 by 17-1/5 inches; 1-year limited warranty",
            "Telescoping handle and low profile for hard-to-reach areas; battery-recharging stand included",
            "Rechargeable 13-inch cordless floor and carpet cleaner with 3-speed electronic control"
        ]
    },
    {
        "ID": "B0009ONZ8Q.html",
        "NAME": "Hoover U5468-900 WindTunnel Supreme Bagged Upright Vacuum Cleaner",
        "CATEGORY": [
            "Home & Kitchen",
            "Vacuums & Floor Care"
        ],
        "DESCRIPTION": [
            "5 height settings; embedded DirtFinder; HEPA filter; full-bag indicator",
            "Measures 13 by 15 by 43 inches; 1-year warranty",
            "2 extension wands, dusting brush, upholstery nozzle, and crevice tool included",
            "12 amp bagged upright vacuum cleaner with WindTunnel technology",
            "15-inch cleaning path; dual brush agitator; edge groomers to clean near baseboards"
        ]
    },
    {
        "ID": "B000NCRY1I.html",
        "NAME": "BLACK+DECKER CHV9608 9.6-Volt Cyclonic-Action Cordless DustBuster with AccuREACH",
        "CATEGORY": [
            "Home & Kitchen",
            "Vacuums & Floor Care",
            "Vacuums",
            "Handheld Vacuums"
        ],
        "DESCRIPTION": [
            "9.6-volt handheld vacuum cleaner with sleek, cordless design",
            "Upholstery brush, VF96 filter, and wall-mountable charging base included",
            "Measures approximately 16-1/2 by 4-1/2 by 7 inches; 2-year warranty",
            "Cyclonic action for long-lasting suction; AccuREACH nozzle offers extended reach",
            "18-ounce removable translucent dust bin empties with 1 easy step"
        ]
    },
    {
        "ID": "B00022NGFW.html",
        "NAME": "Dirt Devil M083414 Extreme Power Cordless Stick Vacuum Cleaner",
        "CATEGORY": [
            "Home & Kitchen",
            "Vacuums & Floor Care",
            "Vacuums",
            "Stick Vacuums & Electric Brooms"
        ],
        "DESCRIPTION": [
            "Cordless stick vacuum cleaner for bare floors and carpets",
            "9-1/2-inch cleaning path; lightweight, low-profile design",
            "14-2/5-volt motor; rotating brush roll; bagless dirt cup",
            "Measures approximately 10 by 8 by 42-1/2 inches; 1-year warranty",
            "Fold-down handle for compact storage; charging base included"
        ]
    },
    {
        "ID": "B000J2PYSW.html",
        "NAME": "Factory-Reconditioned Dyson DC15 The Ball Animal Vacuum",
        "CATEGORY": [
            "Home & Kitchen",
            "Vacuums & Floor Care",
            "Vacuums",
            "Upright Vacuums"
        ],
        "DESCRIPTION": [
            "The vacuum cleaner that doesn't lose suction.",
            "Hygienic and quick to empty bin. No need to touch the dust. Just pull the trigger",
            "Accessories that are included: Mini Turbine Head, Low reach floor tool, Carpet care kit",
            "No extra costs. Lifetime filters that don't clog, no bags to buy",
            "Lifetime HEPA filter. Highest levels of filtration for cleaner expelled air"
        ]
    },
    {
        "ID": "B00020R0XI.html",
        "NAME": "Hoover S3332 Telios Straight Suction Canister Vacuum",
        "CATEGORY": [
            "Home & Kitchen",
            "Vacuums & Floor Care",
            "Vacuums",
            "Canister Vacuums"
        ],
        "DESCRIPTION": [
            "360-degree swivel hose connection; large wheels; automatic cord rewind",
            "Full 1-year warranty",
            "Variable-speed control; sleek design for lightweight maneuverability and versatility",
            "12-amp canister vacuum with 7-stage filtration system and check-bag indicator light",
            "Telescopic wand; dusting brush, furniture nozzle, and crevice tool included"
        ]
    },
    {
        "ID": "B001CIJ66I.html",
        "NAME": "Electrolux 4718AVZ Light Force 300 Upright Vacuum Green",
        "CATEGORY": [
            "Home & Kitchen",
            "Vacuums & Floor Care",
            "Vacuums",
            "Upright Vacuums"
        ],
        "DESCRIPTION": [
            "For quick and easy emptying",
            "For quick and easy use",
            "Extends 3 feet for cleaning ceiling dans, blinds, book case tops and more",
            "For vertical cleaning of stairs and upholstery",
            "For deep cleaning carpets"
        ]
    },
    {
        "ID": "B000GLPU9O.html",
        "NAME": "Eureka Optima Lightweight Upright Vacuum, 437AZ",
        "CATEGORY": [
            "Home & Kitchen",
            "Vacuums & Floor Care",
            "Vacuums",
            "Upright Vacuums"
        ],
        "DESCRIPTION": [
            "12-Amp motor; rotating motorized brushroll cleans rugs, then switches off to gently vacuum hardwoods",
            "Measures 13 by 15 by 44-1/2-inch; weighs 11-4/5-pound; limited 1-year warranty.",
            "Includes stretch hose, dusting brush, crevice wand, and power paw attachment for cleaning stairs, upholstery, and vertical surfaces",
            "Hepa filter captures more than 99.9-percent of dust mites, pollen, ragweed, and other allergens",
            "Lightweight and versatile bagless vacuum combines the performance of an upright with the convenience of a stick"
        ]
    },
    {
        "ID": "B00009R66E.html",
        "NAME": "Hoover U5162-900 Fold Away Bagless Upright Vacuum with Fold Down Handle",
        "CATEGORY": [
            "Home & Kitchen",
            "Vacuums & Floor Care",
            "Vacuums",
            "Upright Vacuums"
        ],
        "DESCRIPTION": [
            "Full-power upright with fold-down handle for easy storage",
            "Allergen filtration traps 99.98 percent of ragweed and pollen",
            "12 by 13 by 43-1/4 inches; 24-1/2 inches high with handle folded",
            "Includes onboard hose, extension wand, crevice tool, dusting brush, and upholstery nozzle",
            "Convenient bagless dirt collection"
        ]
    },
    {
        "ID": "B0009HNH2M.html",
        "NAME": "Hoover Duros Power Nozzle Canister Vacuum, Bagged, S3590",
        "CATEGORY": [
            "Home & Kitchen",
            "Vacuums & Floor Care",
            "Vacuums",
            "Canister Vacuums"
        ],
        "DESCRIPTION": [
            "Variable speed motor with finger-tip on/off switch for brush agitator",
            "14-inch-wide power nozzle brush with headlight",
            "Allergen trapping bags; full bag indicator",
            "360-degree swivel hose on both ends for cleaning flexibility",
            "3 on-board tools; 18-foot cord with cord rewind; 1-year warranty"
        ]
    },
    {
        "ID": "B001DTV27W.html",
        "NAME": "Panasonic MC-CL485 Bagless \"Suction\" Canister Vacuum Cleaner - Corded",
        "CATEGORY": [
            "Home & Kitchen",
            "Vacuums & Floor Care",
            "Vacuums",
            "Canister Vacuums"
        ],
        "DESCRIPTION": [
            "Bagless canister vacuum with a 5-stage filter.",
            "10-Inch Cleaning Path with a Telescopic Chrome Wand that extends for easy reach, Automatic Cord Reel with a 17 Foot cord, Dual Active Edge Cleaning",
            "EZ Fliter Cleaning System by a convenient dial on the outside fo the vacuum spins the filter clean, keeping dirt from getting trapped and helping to ensure consistent suction, Curved Carrying Top Handle makes carrying and maneuvering the vacuum less of a chore",
            "Bagless Canister Vacuum Cleaner offers a powerful 11-AMP Motor, 3-in-1 Multi-Surface Brush without the changing the nozzle-wood floors, short hair carpet or long-hair carpet",
            "Measures: 16.3\" (L) x 11.4\" (W) x 12.6\" (H), 10.1 lbs, Silver"
        ]
    },
    {
        "ID": "B0009WRKRK.html",
        "NAME": "Eureka 426A Optima Lightweight Upright Vacuum",
        "CATEGORY": [
            "Home & Kitchen",
            "Vacuums & Floor Care",
            "Vacuums",
            "Upright Vacuums"
        ],
        "DESCRIPTION": [
            "Large Dust Cup",
            "Telescoping Handle",
            "Very Quiet",
            "Powerful and Lightweight",
            "Best in Class Performance"
        ]
    },
    {
        "ID": "B00022NGF2.html",
        "NAME": "Dirt Devil 088400 Vision Turbo Vacuum",
        "CATEGORY": [
            "Home & Kitchen",
            "Vacuums & Floor Care",
            "Vacuums",
            "Upright Vacuums"
        ],
        "DESCRIPTION": [
            "12-amp upright vacuum for carpets, bare floors, and above-floor cleaning",
            "Onboard stretch hose, motorized Turbo Tool, dusting brush, and crevice tool",
            "Bagless dirt collection and true HEPA filtration to trap 99.97% of allergens",
            "Swivel Casters; triple-row brush roll; quick-release cord hooks",
            "Includes 3-year warranty on parts, 6-year warranty on motor"
        ]
    },
    {
        "ID": "B0009RF81K.html",
        "NAME": "Shark EP750H 18-Volt Cordless 2-in-1 Handheld and Floor Vac with Motorized Brush and Twister Technology",
        "CATEGORY": [
            "Home & Kitchen",
            "Vacuums & Floor Care",
            "Vacuums"
        ],
        "DESCRIPTION": [
            "Cord storage; brush attachment, crevice tool, and charging stand included",
            "Extension tubes turn handheld into a floor vac for cleaning carpet and bare floors",
            "Super-sized detachable motorized brush; HEPA filtration; dust-cup design",
            "Cordless handheld vacuum cleaner with Twister Cyclonic technology",
            "Measures approximately 10 by 4 by 6 inches; 1-year limited warranty"
        ]
    },
    {
        "ID": "B0007918U0.html",
        "NAME": "Bissell 3600A Barbie Real Vacuum, Pink",
        "CATEGORY": [
            "Home & Kitchen",
            "Vacuums & Floor Care",
            "Vacuums",
            "Upright Vacuums"
        ],
        "DESCRIPTION": [
            "Measures 12 by 8-1/2 by 43-3/4 inches; 1-year limited warranty",
            "Easily converts to handheld vacuum; bagless with easy twist-off dustcup",
            "Based on Bissell's popular Go Vac ultra-lightweight vacuum",
            "Cordless vacuum cleaner with rotating brush roll cleans both rugs and carpets",
            "Rechargeable battery; washable filter; 9-inch cleaning path; for ages 6 and older"
        ]
    },
    {
        "ID": "B000R5LVVA.html",
        "NAME": "Hoover FloorMate SpinScrub Wet/Dry Vacuum Cleaner, H3044",
        "CATEGORY": [
            "Home & Kitchen",
            "Vacuums & Floor Care",
            "Vacuums",
            "Upright Vacuums"
        ],
        "DESCRIPTION": [
            "15-inch-wide cleaning path; EZ Select dial; fingertip trigger control",
            "Separate tanks for clean and dirty water",
            "Fold-down handle; 8-ounce grout cleaner and 8-ounce floor-to-floor cleaner included",
            "All-in-one cleaning system vacuums, washes, and dries hard-floor surfaces",
            "Measures approximately 20 by 15-1/2 by 45 inches; 1-year warranty"
        ]
    },
    {
        "ID": "B000B7BWGS.html",
        "NAME": "Eureka 166DX Boss Lightweight Stick Vacuum",
        "CATEGORY": [
            "Home & Kitchen",
            "Vacuums & Floor Care",
            "Vacuums",
            "Stick Vacuums & Electric Brooms"
        ],
        "DESCRIPTION": [
            "Petite stick vacuum styled after Eureka's Boss model; for light cleaning of bare floors and some carpets",
            "Bagless in design with allergen filtration for cleaner air; easy to remove dust cup",
            "Telescopic handle enables upright or handheld use of the extremely lightweight vacuum; 15-foot retractable power cord",
            "2-amp motor; debris bypasses motor and fan while cleaning to prolong life of this appliance",
            "Vacuum measures 5-1/4 by 6-1/10 by 25-1/2 inches in hand-held mode and weighs 3-4/5 pounds; limited 1-year warranty"
        ]
    },
    {
        "ID": "B000FE98K4.html",
        "NAME": "Dirt Devil 091020V Vibe Bagged Upright",
        "CATEGORY": [
            "Home & Kitchen",
            "Vacuums & Floor Care",
            "Vacuums",
            "Upright Vacuums"
        ],
        "DESCRIPTION": [
            "The center power path delivers the superior suction needed for all you cleaning needs both on the floor as well as above the floor cleaning",
            "Powerful 12 amp Motor with MotorGuard gives you all the power you will need to clean your carpets effectively",
            "Long 32 foot cord allows you a much larger cleaning reach",
            "Tools on Board with the automatic Hose tools extends your reach for effortless cleaning in the hard to reach areas"
        ]
    },
    {
        "ID": "B001AQKQ5C.html",
        "NAME": "Eureka 2999DVZ UNO Bagless Upright HEPA Vacuum Cleaner",
        "CATEGORY": [
            "Home & Kitchen",
            "Vacuums & Floor Care",
            "Vacuums",
            "Upright Vacuums"
        ],
        "DESCRIPTION": [
            "Measures 12 by 15 by 43-1/2 inches; 1-year limited warranty",
            "Adjustable height for carpets and bare floors; 15-inch cleaning path",
            "Bagless upright vacuum cleaner with 12 amp motor and HEPA filter",
            "Adjustable telescoping handle; headlight; easy-to-empty dust cup",
            "Includes crevice tool, dusting brush, turbo nozzle, and self-cleaning duster"
        ]
    },
    {
        "ID": "B00008W6QH.html",
        "NAME": "Eureka 4696AV Whirlwind Bagless Cyclonic True HEPA Upright Vacuum",
        "CATEGORY": [
            "Home & Kitchen",
            "Vacuums & Floor Care",
            "Vacuums",
            "Upright Vacuums"
        ],
        "DESCRIPTION": [
            "Bagless cyclonic system; 12-amp motor",
            "Awarded the Good Housekeeping Seal of Approval",
            "HEPA filter; large dust cup",
            "15-inch cleaning path; stretch hose; onboard tools",
            "1-year warranty on parts, 90 days on labor"
        ]
    },
    {
        "ID": "B0007Z69G2.html",
        "NAME": "Bissell Aeroswift Compact Bagless Upright Vacuum, 1009 - Corded",
        "CATEGORY": [
            "Home & Kitchen",
            "Vacuums & Floor Care",
            "Vacuums",
            "Upright Vacuums"
        ],
        "DESCRIPTION": [
            "Tools included with the Bissell vacuum: rotating TurboBrush tool, extension wand, crevice tool and easy comfort quick-release handle",
            "Cyclonic technology extends performance and keeps filters cleaner and longer",
            "5 height settings adjustable for different carpet lengths",
            "Quick release handle to easily transition from cleaning floors to stairs and other hard to reach areas, complete with a 10' reach",
            "Bottom empty dirt bin designed for easy and touch less dirt disposal"
        ]
    },
    {
        "ID": "B000C524LG.html",
        "NAME": "Sanyo SC-S700P Powerhead Canister Vacuum Cleaner",
        "CATEGORY": [
            "Home & Kitchen",
            "Vacuums & Floor Care",
            "Vacuums",
            "Canister Vacuums"
        ],
        "DESCRIPTION": [
            "12-amp motor for plenty of sucking power",
            "Powerhead brush provides exceptional cleaning and strong suction",
            "20-foot cord with push-button cord reel",
            "8-piece tool set for a wide variety of cleaning applications",
            "Convenient carrying handle and lightweight design"
        ]
    },
    {
        "ID": "B0009RF81A.html",
        "NAME": "Shark SV736N 15.6-Volt Cordless Handheld Vacuum Cleaner with Motorized Brush, Colors Vary",
        "CATEGORY": [
            "Home & Kitchen",
            "Vacuums & Floor Care",
            "Vacuums",
            "Handheld Vacuums"
        ],
        "DESCRIPTION": [
            "Crevice tool for hard-to-reach spots; washable filter; convenient dust cup",
            "LED charging and low-battery indicator;",
            "Cordless handheld vacuum cleaner with Twister Cyclonic technology",
            "Detachable motorized brush removes pet hair and dirt from upholstery and carpet",
            "Measures approximately 10 by 4 by 6 inches; 1-year limited warranty"
        ]
    },
    {
        "ID": "B0009WRKRA.html",
        "NAME": "Eureka 409B The Boss Superlite Widetrack Vacuum",
        "CATEGORY": [
            "Home & Kitchen",
            "Vacuums & Floor Care",
            "Vacuums",
            "Upright Vacuums"
        ],
        "DESCRIPTION": [
            "3-amp motor; transparent easy-empty dirt cup",
            "Rotating motorized brushroll cleans rugs, then switches off to gently vacuum hardwoods",
            "Telescoping handle folds flat for compact storage",
            "Ultra-lightweight and maneuverable bagless vacuum with versatile two-motor system",
            "Measures 12 by 6 by 27-1/3 inches; weighs 8 pounds; 1-year limited warranty"
        ]
    },
    {
        "ID": "B0001Z84L6.html",
        "NAME": "Hoover U5262-900 EmPower Vacuum",
        "CATEGORY": [
            "Home & Kitchen",
            "Vacuums & Floor Care",
            "Vacuums",
            "Upright Vacuums"
        ],
        "DESCRIPTION": [
            "Power Boost for hard-to-clean messes",
            "Hush mode provides quiet cleaning; allergen filtration system",
            "Versatile, 12-amp vacuum cleaner comes fully assembled",
            "5 height-adjustment settings; upper handle folds down for easy storage",
            "Measures 15-inches wide; full 1-year warranty"
        ]
    },
    {
        "ID": "B0007LJO2C.html",
        "NAME": "Dyson DC14 All-Floors Cyclone Upright Vacuum Cleaner",
        "CATEGORY": [
            "Home & Kitchen",
            "Vacuums & Floor Care",
            "Vacuums",
            "Upright Vacuums"
        ],
        "DESCRIPTION": [
            "Hygienic 5/7-gallon dust bin; lifetime HEPA filter; certified asthma friendly",
            "Quick-draw Telescope reach; edge-cleaning whiskers; wide channel",
            "All-floors upright vacuum cleaner with motorized brushbar",
            "Measures 13-3/8 by 14 by 44-6/7 inches; 5-year warranty",
            "Root Cyclone technology ensures powerful, continuous suction"
        ]
    },
    {
        "ID": "B000OVXC5U.html",
        "NAME": "Rainbow E Series Canister Vacuum Cleaner Wet / Dry",
        "CATEGORY": [
            "Home & Kitchen",
            "Vacuums & Floor Care",
            "Vacuums",
            "Canister Vacuums"
        ],
        "DESCRIPTION": [
            "Includes bushy-brush bare floor tool and extra wands",
            "Water filtration for clean, odor-free air as you vacuum",
            "Complete outfit with all standard accessories",
            "2-motor design",
            "Superior cleaning power for homes with pets"
        ]
    },
    {
        "ID": "B000HZEOS2.html",
        "NAME": "Hoover U831900 Windtunnel 2 Bagged Upright Vacuum Cleaner",
        "CATEGORY": [
            "Home & Kitchen",
            "Vacuums & Floor Care",
            "Vacuums",
            "Upright Vacuums"
        ],
        "DESCRIPTION": [
            "Telescoping quick-release wand and super-stretch hose; 28-foot cord",
            "Measures approximately 14 by 15 by 43 inches; 1-year warranty",
            "12 amp upright vacuum cleaner with WindTunnel 2 technology",
            "Dusting brush, furniture nozzle, crevice tool, and pet-hair tool included",
            "DirtFinder system; automatic brush-roll shutoff for above-floor cleaning"
        ]
    },
    {
        "ID": "B000WSCOMM.html",
        "NAME": "Dirt Devil Refurbished R082550 Breeze Vision Bagless Canister with Power Pak Nozzle",
        "CATEGORY": [
            "Home & Kitchen",
            "Vacuums & Floor Care",
            "Vacuums",
            "Canister Vacuums"
        ],
        "DESCRIPTION": [
            "Refurbished to be like new",
            "With 12 amp power, this unit is as powerful as an upright",
            "Features all-surface cleaning in a lightweight and compact design Perfect for cleaning bare or carpeted floors",
            "Got allergies? Fight back with the breeze vision canister As an additional guard against dust and allergens, this cleaner features microfresh filtration system which easily captures over 99-percent of dust and allergens that linger in your home",
            "20-Foot power cord with built in cord wrap for easystorage, lets you easily clean from room to room"
        ]
    },
    {
        "ID": "B000ML1DNU.html",
        "NAME": "Kenmore Magic Blue 24195 Bagged Canister Vacuum",
        "CATEGORY": [
            "Home & Kitchen",
            "Vacuums & Floor Care",
            "Vacuums",
            "Canister Vacuums"
        ],
        "DESCRIPTION": [
            "Telescopic Wand",
            "Cord Rewind",
            "Handle Controls",
            "Bag Change",
            "Cup Full Indicator"
        ]
    },
    {
        "ID": "B0015YULO0.html",
        "NAME": "ROTHO Twin TT Water-Filtration HEPA Canister Vacuum Cleaner by Robert Thomas LP",
        "CATEGORY": [
            "Home & Kitchen",
            "Vacuums & Floor Care",
            "Vacuums",
            "Canister Vacuums"
        ],
        "DESCRIPTION": [
            "ROTHO Twin TT home cleaning system"
        ]
    },
    {
        "ID": "B00006IIV4.html",
        "NAME": "Hoover U5720-900 WindTunnel Bagless",
        "CATEGORY": [
            "Home & Kitchen",
            "Vacuums & Floor Care",
            "Vacuums",
            "Upright Vacuums"
        ],
        "DESCRIPTION": [
            "31-foot cord with quick release hooks",
            "Bagless twin-chamber dirt collection",
            "One HEPA filter plus two others for reduced allergens",
            "Measures 15 by 12-3/4 by 43 inches",
            "Side-mounted hose and on-board attachments"
        ]
    },
    {
        "ID": "B00008J4C7.html",
        "NAME": "Shark Roadster Canister Vacuum -Ep722 - (Power Pet) Factory Serviced",
        "CATEGORY": [
            "Home & Kitchen",
            "Vacuums & Floor Care",
            "Vacuums",
            "Canister Vacuums"
        ],
        "DESCRIPTION": [
            "Item # : TG-EP722-FS",
            "Free Shipping within the lower 48 contiguous (USA states)",
            "Dimensions: 14.5\" L x 11\" W x 10\" H"
        ]
    },
    {
        "ID": "B00009R66C.html",
        "NAME": "Hoover U6439-900 Self-Propelled WindTunnel Ultra Upright Vacuum Cleaner",
        "CATEGORY": [
            "Home & Kitchen",
            "Vacuums & Floor Care",
            "Vacuums",
            "Upright Vacuums"
        ],
        "DESCRIPTION": [
            "Onboard hose and attachments, including powered hand tool",
            "Embedded Dirt Finder system",
            "Self-propelled locomotion with WindTunnel technology",
            "Allergen filtration with HEPA filter",
            "14 by 15 by 43 inches"
        ]
    },
    {
        "ID": "B000IBDSVY.html",
        "NAME": "Eureka Maxima Upright Vacuum, 4711BZ",
        "CATEGORY": [
            "Home & Kitchen",
            "Vacuums & Floor Care",
            "Vacuums",
            "Upright Vacuums"
        ],
        "DESCRIPTION": [
            "Allergen filter",
            "Integrated Hose",
            "Lightweight",
            "Bagless",
            "12 amps of power"
        ]
    },
    {
        "ID": "B0012XMT2G.html",
        "NAME": "Remanufactured Dyson DC17 Animal Cyclone Upright Vacuum Cleaner",
        "CATEGORY": [
            "Home & Kitchen",
            "Vacuums & Floor Care",
            "Vacuums",
            "Upright Vacuums"
        ],
        "DESCRIPTION": [
            "Quick-draw Telescope reach; mini turbine head; low-reach floor tool",
            "All-floors upright vacuum cleaner with motorized brushbar",
            "Measures 26-2/3 by 13-1/5 by 43-1/2 inches; 6-month warranty",
            "Hygienic 5/8-gallon dust bin; lifetime HEPA filter;",
            "Level 3 Root Cyclone technology ensures powerful, consistent suction"
        ]
    },
    {
        "ID": "B000NCRYYA.html",
        "NAME": "BLACK+DECKER CHV1568 15.6 -Volt Cyclonic-Action Cordless DustBuster with AccuREACH",
        "CATEGORY": [
            "Home & Kitchen",
            "Vacuums & Floor Care",
            "Vacuums",
            "Handheld Vacuums"
        ],
        "DESCRIPTION": [
            "Cordless 15.6-volt handheld vacuum cleaner with 3-stage filtration",
            "19-ounce dust bin; VF08 filter and wall-mountable charging base included",
            "Measures approximately 17 by 5 by 7 inches; 2-year warranty",
            "AccuREACH nozzle offers extended reach; crevice tool and upholstery brush",
            "Cyclonic action ensures long-lasting suction power; EZ clean dial cleans filter"
        ]
    },
    {
        "ID": "B001BFFVO8.html",
        "NAME": "Dirt Devil Vision Bagless Canister Vacuum with Power Nozzle, M082750",
        "CATEGORY": [
            "Home & Kitchen",
            "Vacuums & Floor Care",
            "Vacuums",
            "Canister Vacuums"
        ],
        "DESCRIPTION": [
            "Swivel casters; headlight; 18-foot power cord; automatic cord rewind",
            "Measures approximately 14-4/5 by 12-2/5 by 26-1/2 inches; 2-year limited warranty",
            "Full-size 12 amp bagless canister vacuum cleaner with power nozzle",
            "Variable speed adjustment; on-board cleaning tools; dirt cup; HEPA filter",
            "On/off motorized brushroll for thorough carpet cleaning; 6-position head adjustment"
        ]
    },
    {
        "ID": "B000I17C5W.html",
        "NAME": "Hoover Powered Hand Tool, 40200013",
        "CATEGORY": [
            "Home & Kitchen",
            "Vacuums & Floor Care",
            "Vacuums"
        ],
        "DESCRIPTION": [
            "Turbined Powered agitator to clean upholstry, furniture, stairs and car interiors"
        ]
    },
    {
        "ID": "B000WS0DSE.html",
        "NAME": "Hoover Reconditioned WindTunnel Upright Vacuum, Bagged, U54219RM",
        "CATEGORY": [
            "Home & Kitchen",
            "Vacuums & Floor Care",
            "Vacuums",
            "Upright Vacuums"
        ],
        "DESCRIPTION": [
            "Front tool storage places tools within easy reach Tool set includes: An attached hose, two extension wands, dusting brush, upholstry nozzle, and crevice tool",
            "Embedded Dirtfinder Sensing Technology tells you when your carpet is clean",
            "Allergen Filtration traps 100% of dust mites, ragweed, and common grass pollens",
            "Reconditioned like new",
            "Powerful 12 amp motor with patented Windtunnel Technology"
        ]
    },
    {
        "ID": "B000Q9X9TY.html",
        "NAME": "BLACK+DECKER AV1500 DustBuster 12V Auto Vac",
        "CATEGORY": [
            "Home & Kitchen",
            "Vacuums & Floor Care",
            "Vacuums",
            "Handheld Vacuums"
        ],
        "DESCRIPTION": [
            "16' Power cord with 12V vehicle power adaptor for extended reach and convenience",
            "On-board accessory storage so DustBuster tools go where you need them",
            "One-step empty means hands never touch the dirt"
        ]
    },
    {
        "ID": "B0009FUC7C.html",
        "NAME": "Bissell Remanufactured 6594R PowerForce Bagless Upright Vacuum",
        "CATEGORY": [
            "Home & Kitchen",
            "Vacuums & Floor Care",
            "Vacuums",
            "Upright Vacuums"
        ],
        "DESCRIPTION": [
            "12 amp motor for high-suction capability; lightweight, maneuverable design",
            "Remanufactured to like-new condition; 90-day warranty",
            "Powerful upright vacuum with convenient bagless technology",
            "Includes extra-long stretch hose, upholstery/dusting brush, crevice tool, and extension wand",
            "Easy-to-empty dirt container replaces disposable bags"
        ]
    },
    {
        "ID": "B0009SU03A.html",
        "NAME": "Bissell 3595 CleanView Revolution Upright Bagless Vacuum",
        "CATEGORY": [
            "Home & Kitchen",
            "Vacuums & Floor Care",
            "Vacuums",
            "Upright Vacuums"
        ],
        "DESCRIPTION": [
            "HEPA media filter captures over 99.9 percent of dust mites, pollens and ragweed",
            "Bagless upright vacuum with clear plastic debris container for easy dumping",
            "15-inch cleaning path for optimal coverage",
            "Onboard tools snap on tightly and stay put for easy access",
            "TurboBrush removes deeply embedded pet hair and more"
        ]
    },
    {
        "ID": "B0016J5AZO.html",
        "NAME": "Eureka 442B SuperLite Bagless Upright Vacuum Cleaner",
        "CATEGORY": [
            "Home & Kitchen",
            "Vacuums & Floor Care",
            "Vacuums",
            "Upright Vacuums"
        ],
        "DESCRIPTION": [
            "Easy-empty dust cup with allergen filtration for quick disposal of dirt and dust",
            "12-inch-wide cleaning path; 20-foot quick-release cord; telescopic handle",
            "Measures 6 by 12 by 27-2/7 inches; 1-year warranty",
            "Bagless, upright vacuum cleaner with 3-1/2 amps of power",
            "2-motor system provides on/off brush roll; weighs less than 8 pounds"
        ]
    },
    {
        "ID": "B000CQP8TA.html",
        "NAME": "Hoover U9145-900 Z 700 Bagless Upright Vacuum",
        "CATEGORY": [
            "Home & Kitchen",
            "Vacuums & Floor Care",
            "Vacuums",
            "Upright Vacuums"
        ],
        "DESCRIPTION": [
            "Lifetime LED headlights; Full two-year warranty",
            "Z-Fold design vacuum with self-cleaning HEPA filter",
            "Telescoping quick-release wand with super-stretch hose combine for 20 feet of cleaning reach",
            "DigiTouch control pad at your fingertips to switch settings",
            "Includes pet hair cleaning tool, extra 16-inch cleaning wand, and 14-inch floor brush"
        ]
    },
    {
        "ID": "B00008URRT.html",
        "NAME": "Westinghouse WST1600A Unplugged Cord-Free Vacuum",
        "CATEGORY": [
            "Home & Kitchen",
            "Vacuums & Floor Care",
            "Vacuums",
            "Upright Vacuums"
        ],
        "DESCRIPTION": [
            "Interchangeable power packs never leave you without power",
            "14-amps -- more than any corded vacuum",
            "Long-life HEPA filter lasts 7 years",
            "Rotating brush shuts off for bare floor cleaning",
            "No bags to buy or broken belts to replace"
        ]
    },
    {
        "ID": "B00083YK2I.html",
        "NAME": "Hoover U5170-900 Fold Away Widepath Bagless Upright Vacuum",
        "CATEGORY": [
            "Home & Kitchen",
            "Vacuums & Floor Care",
            "Vacuums",
            "Upright Vacuums"
        ],
        "DESCRIPTION": [
            "Allergen filtration system captures dust mites, ragweed, common pollens",
            "Dusting brush, furniture nozzle, crevice tool, extension wand",
            "Deluxe triple stretch hose; 1-year warranty",
            "Lightweight and maneuverable; folding handle for easy storage",
            "Powerful 12 amp motor; 15-inch cleaning path"
        ]
    },
    {
        "ID": "B0002600YI.html",
        "NAME": "Panasonic MC-4620 Bagless Straight-Suction Canister Vacuum",
        "CATEGORY": [
            "Home & Kitchen",
            "Vacuums & Floor Care",
            "Vacuums",
            "Canister Vacuums"
        ],
        "DESCRIPTION": [
            "11-amp canister vacuum with 12-inch cleaning path; ideal for bare floors",
            "5-stage filtration system; 2-1/2-quart dirt cup means no more bags to buy",
            "One-year parts-and-labor warranty",
            "Blower operation; filter maintenance device; filter-check indicator",
            "Compact design and lightweight; 17-foot cord; cord reel; easy-stand storage"
        ]
    },
    {
        "ID": "B00006IIV5.html",
        "NAME": "Hoover U8120-900 WindTunnel V2 Bagged",
        "CATEGORY": [
            "Home & Kitchen",
            "Vacuums & Floor Care",
            "Vacuums",
            "Upright Vacuums"
        ],
        "DESCRIPTION": [
            "High-powered WindTunnel V2 bagged vacuum with onboard tools",
            "Measures 15 by 14 by 43-1/2 inches",
            "HEPA allergen filtration traps dust mites, pollen, and dander",
            "Dual agitator brush rolls and soft, non-marring wheels",
            "Dual air path directs cleaning power to edges"
        ]
    },
    {
        "ID": "B000HRY304.html",
        "NAME": "Bissell 3990 Total Floors Velocity Bagless Upright Vacuum Cleaner",
        "CATEGORY": [
            "Home & Kitchen",
            "Vacuums & Floor Care",
            "Vacuums",
            "Upright Vacuums"
        ],
        "DESCRIPTION": [
            "Colors may vary, green or blue",
            "Multi-stage filtration keep filters clean longer for continuous suction power",
            "12 amp, multi-surface upright vacuum cleaner with cyclone technology for better suction",
            "Foot-activated brush off pedal and scatter shield for superior bare-floor cleaning",
            "Total floor cleaning-rotating brush action for deep down cleaning,"
        ]
    },
    {
        "ID": "B0009BO2TA.html",
        "NAME": "Hoover Portable Canister, S1361",
        "CATEGORY": [
            "Home & Kitchen",
            "Vacuums & Floor Care",
            "Vacuums",
            "Canister Vacuums"
        ],
        "DESCRIPTION": [
            "8-amp bagged canister vacuum perfect for small spaces or smaller clean-up jobs",
            "Full one-year warranty",
            "Variable speed motor; straight suction canister for bare floors and carpets",
            "10-inch nozzle, telescoping wand; 6-foot cord, 360-degree swivel hose",
            "On-board features include a dusting brush and crevice tool, full-bag indicator, and automatic cord rewind"
        ]
    },
    {
        "ID": "B0013HX70O.html",
        "NAME": "Portable Handheld Cordless Vacuum Cleaner - Compact Hand-held Bagless Floor Stick Cyclonic Suction w/ HEPA Filter, Canister, Rechargeable Battery, Captures Dust and Pet Hair - Pyle PUCVCBAT48",
        "CATEGORY": [
            "Industrial & Scientific",
            "Janitorial & Sanitation Supplies",
            "Vacuums & Floor Cleaning Machines",
            "Vacuums",
            "Handheld Vacuums"
        ],
        "DESCRIPTION": [
            "CORDLESS HANDHELD DESIGN: This portable cordless vacuum cleaner features a hassle-free design, along with simple wireless operation, making for quick clean-ups all within arm\u2019s reach while adding mobility to your cleaning routine",
            "SIMPLE TO USE: The bagless stick vacuum is efficient as it is easy to use with simple push-button operation. It comes with a handy collection of attachment accessories including a rotating brush to make vacuuming as thorough as possible",
            "MULTI-SURFACE CLEANING ABILITY: The Pure Clean vacuum cleaner features Cyclone 'Power-Spin' technology. Equipped w/ built-in HEPA filter that captures extra fine dust, dirt, pet hair, and an adjustable tube arm that extends for hard-to-reach areas",
            "HIGH POWERED SUCTION: This handheld vacuum cleaner made of engineered ABS features a built-in rechargeable battery with an average charge time of 3.5 hours. The bagless vacuum cleaner features a vacuum suction power of up to 11kPa",
            "EASY DISPOSAL OF WASTE: This lightweight and compact hand vacuum cleaner removes collected wastes via the easy access dustbin. You can also see the collection level thanks to the transparent \u2018see-through\u2019 container housing"
        ]
    },
    {
        "ID": "B00022NGFM.html",
        "NAME": "Dirt Devil CE5500 Floor Keeper",
        "CATEGORY": [
            "Home & Kitchen",
            "Vacuums & Floor Care",
            "Vacuums",
            "Upright Vacuums"
        ],
        "DESCRIPTION": [
            "Cleans in forward and reverse for more efficient coverage",
            "13-1/4 by 9-3/4 by 42-1/2 inches; 2-year warranty; 2 starter bottles of cleaner",
            "Double tank design; soft wheels; 13-inch floor nozzle; 25-foot cord",
            "Wet and dry floor cleaner to vacuum, wash, and dry",
            "Suitable for all sealed floors, including hardwood, tile, marble, linoleum, and vinyl"
        ]
    },
    {
        "ID": "B000L3SD0U.html",
        "NAME": "Infinuvo CleanMate QQ-2 Robotic Vacuum with Self-charging Base (White)",
        "CATEGORY": [
            "Home & Kitchen",
            "Vacuums & Floor Care",
            "Vacuums",
            "Robotic Vacuums"
        ],
        "DESCRIPTION": [
            "UV light provides disinfection",
            "Auto-off feature conserves power when unit is not in use and being recharging",
            "Resumes cleaning after battery recharge completion",
            "3 1/2 hours quick battery charging",
            "Automatically returns to dock for self-recharging when low on battery power"
        ]
    },
    {
        "ID": "B000N3YBNQ.html",
        "NAME": "Electrolux EL5020A Intensity Upright Vacuum Cleaner",
        "CATEGORY": [
            "Home & Kitchen",
            "Vacuums & Floor Care",
            "Vacuums",
            "Upright Vacuums"
        ],
        "DESCRIPTION": [
            "Measures 17 by 12 by 14 inches when folded down; 2-year warranty",
            "HEPA filtration; 1-quart bag capacity; bi-fold handle; retractable 21-foot cord",
            "Upright vacuum cleaner with 12 amp motor and 3-inch air path for maximum suction",
            "Fingertip controls; carpet and bare-floor modes; 12-inch-wide cleaning path",
            "Helpful indicator lights; adjustable-height telescopic handle for comfortable use"
        ]
    },
    {
        "ID": "B001EYILAW.html",
        "NAME": "Bissell PROdry Fast-Drying Carpet Cleaner, 7350",
        "CATEGORY": [
            "Home & Kitchen",
            "Vacuums & Floor Care",
            "Vacuums"
        ],
        "DESCRIPTION": [
            "Includes 16-ounce Fiber Cleansing Formula and trial-size OxyGen2",
            "TLR PowerRoller floor brush traps, lifts, and removes dirt and debris",
            "Measures approximately 18 by 12 by 43-1/2 inches; 1-year limited warranty",
            "Dries in 30 minutes; 8-foot hose; tough-stain tool and OxyGen2 PowerTool",
            "Fast-drying carpet cleaner cleans both carpets and area rugs"
        ]
    },
    {
        "ID": "B0009K9RL4.html",
        "NAME": "Hoover U5262-910 EmPower Bagless Upright Vacuum",
        "CATEGORY": [
            "Home & Kitchen",
            "Vacuums & Floor Care",
            "Vacuums",
            "Upright Vacuums"
        ],
        "DESCRIPTION": [
            "12-amp motor features push-button power surge for heavy-duty dirt extraction; 5 height settings available for various carpets and floors",
            "Vacuum weighs 21 pounds upon shipping; 1-year warranty",
            "Bagless upright vacuum with 15-inch cleaning path from Hoover; hush mode available for quiet cleaning",
            "Onboard accessories include hand-held power tool for pet hair and vertical cleaning; with a 31-foot power cord and fold-down handle",
            "Teflon-coated HEPA filtration cartridge removes air impurities and allergens; debris collects in removable double-chamber dust cup"
        ]
    },
    {
        "ID": "B0009PRJYQ.html",
        "NAME": "Eureka Boss 4D Upright Vacuum (Yellow) 5892BVZ",
        "CATEGORY": [
            "Home & Kitchen",
            "Vacuums & Floor Care",
            "Vacuums",
            "Upright Vacuums"
        ],
        "DESCRIPTION": [
            "Power Paw Turbo",
            "Sealed HEPA System",
            "Two Motor System",
            "Deluxe 15\" Furniture Guard",
            "Self-Cleaning Duster"
        ]
    },
    {
        "ID": "B0009OAG5G.html",
        "NAME": "Eureka 2924AS Contour Upright Vacuum with Bonus SpinDuster and Stick Vac",
        "CATEGORY": [
            "Home & Kitchen",
            "Vacuums & Floor Care",
            "Vacuums",
            "Upright Vacuums"
        ],
        "DESCRIPTION": [
            "Powerful 12 amp upright vacuum with bonus SpinDuster and Stick Vac",
            "3-to-1 stretch hose maximizes cleaning length; HEPA filter captures 99.97 of all dust and allergens",
            "SpinDuster magnetically attracts dust and sucks it into vacuum container",
            "Wide 15-inch cleaning path is 25 percent larger than standard vacuums",
            "Lightweight Stick Vac includes floor nozzle and telescoping handle; 1-year warranty"
        ]
    },
    {
        "ID": "B0000TF49I.html",
        "NAME": "iRobot Roomba 3100 Pro Elite Robotic Floor Vacuum",
        "CATEGORY": null,
        "DESCRIPTION": [
            "Automatically vacuums floors without supervision",
            "Transitions between low-to-medium-pile carpet, hardwoods, tile, and linoleum",
            "3-stage system cleans wall edges, under furniture, and concentrated spots",
            "Includes remote control, 2 virtual walls to keep Roomba contained; 1 rechargeable battery",
            "Wall mount also included; measures 13 by 3-1/4 inches"
        ]
    },
    {
        "ID": "B000BRGMSQ.html",
        "NAME": "iRobot Roomba Intelligent Floorvac Robotic Vacuum, Red",
        "CATEGORY": [
            "Home & Kitchen",
            "Vacuums & Floor Care",
            "Vacuums",
            "Robotic Vacuums"
        ],
        "DESCRIPTION": [
            "Measures approximately 13 by 4 inches; 1-year warranty",
            "Rechargeable APS battery, 7-hour charger, 1 virtual wall, and air filter included",
            "Edge-cleaning sidebrush; stasis sensor; virtual wall for confining to designated area",
            "Auto adjusts to any floor surface; 2-hour continuous cleaning; easy-to-empty debris bin",
            "Entry-level robotic floorvac with dirt detection and infra-red cliff sensors"
        ]
    },
    {
        "ID": "B0009RF810.html",
        "NAME": "Shark SV738 10.8 Volt Cordless Hand Vac with Twister Technology",
        "CATEGORY": [
            "Home & Kitchen",
            "Vacuums & Floor Care",
            "Vacuums",
            "Handheld Vacuums"
        ],
        "DESCRIPTION": [
            "Rated number 1 best-cleaning hand vac for picking up most dirt",
            "Convenient dust cup design requires no replacement bags",
            "Twister cyclonic technology for longer, stronger suction",
            "Includes dusting brush, crevice tool, and charging stand",
            "Comfortable rubber grip; detachable, washable filter"
        ]
    },
    {
        "ID": "B000069BFC.html",
        "NAME": "Euro-Pro Shark EP704SH Spectra Upright Vacuum",
        "CATEGORY": [
            "Home & Kitchen",
            "Vacuums & Floor Care",
            "Vacuums",
            "Upright Vacuums"
        ],
        "DESCRIPTION": [
            "Handles pivots 90 degrees to clean in spaces only 8 inches high",
            "4-position carpet-height adjustment",
            "Slim, 1440-watt, full-size upright vacuum weighs just 13 pounds",
            "Extra-large wheels for easy maneuverabilty",
            "Dusting brush and crevice tool included; bag-full indicator"
        ]
    },
    {
        "ID": "B000N20MTE.html",
        "NAME": "Dirt Devil M085850 Featherlite Bagless Upright Vacuum Cleaner",
        "CATEGORY": [
            "Home & Kitchen",
            "Vacuums & Floor Care",
            "Vacuums",
            "Upright Vacuums"
        ],
        "DESCRIPTION": [
            "No-hassle, clean-release dirt container empties quickly and easily",
            "Microfresh filtration traps up to 99 percent of dust and allergens",
            "On-board hose and tools for extended cleaning reach; stair-cleaning handle",
            "Measures 12-1/2 by 12 by 44-1/2 inches; 1-year warranty",
            "Full-size, bagless, upright vacuum cleaner with lightweight design"
        ]
    },
    {
        "ID": "B000AAWEK4.html",
        "NAME": "Miele S4210 Galaxy Canister Vacuum Cleaners",
        "CATEGORY": [
            "Home & Kitchen",
            "Vacuums & Floor Care",
            "Vacuums",
            "Canister Vacuums"
        ],
        "DESCRIPTION": [
            "Dimensions - Height 8 x Width 9 x Length 19",
            "Weight - 11 pounds"
        ]
    },
    {
        "ID": "B001JAGYLY.html",
        "NAME": "Hoover Elite Cyclonic Canister, S3825",
        "CATEGORY": [
            "Home & Kitchen",
            "Vacuums & Floor Care",
            "Vacuums",
            "Canister Vacuums"
        ],
        "DESCRIPTION": [
            "Fingertip controls adjust suction-control valve or turn brushroll on/off",
            "Multi-stage cyclonic technology separates dust and debris; HEPA media filter",
            "12 amp bagless canister vacuum cleaner for carpets and bare-floor surfaces",
            "Adjustable-height wand; on-board attachments; bottom-empty dirt cup; cord rewind",
            "Measures approximately 26 by 16 by 15-4/5 inches"
        ]
    },
    {
        "ID": "B00008OIG5.html",
        "NAME": "Miele : S163 Universal Mini Upright Vacuum - Black",
        "CATEGORY": [
            "Home & Kitchen",
            "Vacuums & Floor Care",
            "Vacuums"
        ],
        "DESCRIPTION": [
            "IntensiveClean Dust bags TYPE KK",
            "Combination Floor Tool",
            "Two Speed Power Selecter",
            "Universal enough to use everywhere",
            "Two Speed Power Selector"
        ]
    },
    {
        "ID": "B00008UI0R.html",
        "NAME": "Hoover WindTunnel Canister Vacuum, Electronic Bagless, S3765-040",
        "CATEGORY": [
            "Home & Kitchen",
            "Vacuums & Floor Care",
            "Vacuums",
            "Canister Vacuums"
        ],
        "DESCRIPTION": [
            "Deluxe pump handle design allows for near effortless control and operation",
            "15 Power Nozzle styling has a low profile design for cleaning tough-to-get-at reach places",
            "Includes HEPA filter and 1-year warranty",
            "Bagless cansister vacuum with WindTunnel Technology",
            "Finger-Touch Variable Speed Control provides flexibility in varying suction"
        ]
    },
    {
        "ID": "B001DSK9V8.html",
        "NAME": "Hoover Commercial Lightweight Backpack Vacuum, C2401",
        "CATEGORY": [
            "Industrial & Scientific",
            "Janitorial & Sanitation Supplies",
            "Vacuums & Floor Cleaning Machines",
            "Vacuums",
            "Canister Vacuums"
        ],
        "DESCRIPTION": [
            "Chiropractor designed harness reduces user strain",
            "Extra long, 48 foot 3-wire quick change power cord- switch outlets less often between cleans",
            "Quiet Operation- clean without disrupting the environment around you",
            "Includes an accessory pack with 6\" crevice tool, 11\" turbo floor tool, 2\" dusting brush and 4\" upholstery tool",
            "Lightweight design weighs less than 10 pounds allows for superior mobility"
        ]
    },
    {
        "ID": "B00006IV1E.html",
        "NAME": "Bissell 2100 Sweeper",
        "CATEGORY": [
            "Home & Kitchen",
            "Vacuums & Floor Care",
            "Sweepers & Accessories"
        ],
        "DESCRIPTION": [
            "Compact easy storage",
            "Extremely lightweight and versatile",
            "Ideal for both carpets and floors",
            "Heavy-duty polystyrene construction",
            "High-performance patented bristle brush"
        ]
    },
    {
        "ID": "B00022HYJ6.html",
        "NAME": "iRobot Roomba 4210 Discovery Vacuuming Robot, White",
        "CATEGORY": [
            "Home & Kitchen",
            "Vacuums & Floor Care",
            "Vacuums",
            "Robotic Vacuums"
        ],
        "DESCRIPTION": [
            "Rechargeable APS battery, 3-hour charger, 2 virtual walls, 2 air filters, and remote control included",
            "Edge-cleaning sidebrush; stasis sensor; virtual wall for confining to designated area",
            "Robotic floorvac with dirt detection and convenient infra-red cliff sensors",
            "Measures 16-3/4 by 21 by 5 inches; 1-year warranty",
            "Auto adjusts to any floor surface; 2-hour continuous cleaning; easy-to-empty debris bin"
        ]
    },
    {
        "ID": "B0009ONZ8G.html",
        "NAME": "Hoover Vacuum Cleaner Tempo WidePath Bagged Corded Upright Vacuum U5140900",
        "CATEGORY": [
            "Home & Kitchen",
            "Vacuums & Floor Care",
            "Vacuums",
            "Upright Vacuums"
        ],
        "DESCRIPTION": [
            "25 Foot Power Cord - plenty of cord to vacuum larger rooms",
            "Bag made with Allergen Media - Media filters and traps 99% of dust and pollens down to 5 microns",
            "Fabulous Filtration - air passes through rinsable filters after leaving the bag and before it leaves the vacuum, so you can breathe easy",
            "Rinsable Filter - Rinse and reuse for long-lasting convenience",
            "Widepath Cleaning - 15\" cleaner width gets the job done quickly",
            "Includes 2 extension wands, crevice tool, upholstery tool and dusting brush"
        ]
    },
    {
        "ID": "B000CDHO40.html",
        "NAME": "BLACK+DECKER CCV1000 CycloPro Cyclonic Corded Hand Vac with Turbo Brush",
        "CATEGORY": [
            "Home & Kitchen",
            "Vacuums & Floor Care",
            "Vacuums",
            "Handheld Vacuums"
        ],
        "DESCRIPTION": [
            "Easy empty dirt chamber so hands don't touch the dirt",
            "Cyclonic action spins the dirt, keeping the filter clean and the suction power strong",
            "Turbo brush included for deep cleaning carpets, Includes HEPA filtration",
            "On-board crevice and brush tool, Cord wrap system for quick and easy storage",
            "Patented dual dirt chambers separate the fine dirt and dust far away from the filter ensuring continuous power 2X longer than any other hand vac in the market"
        ]
    },
    {
        "ID": "B0009SU030.html",
        "NAME": "Bissell 20Q9 CleanView II Plus Upright Bagless Vacuum",
        "CATEGORY": [
            "Home & Kitchen",
            "Vacuums & Floor Care",
            "Vacuums",
            "Upright Vacuums"
        ],
        "DESCRIPTION": [
            "7 height adjustments; 27-foot power cord; 1-year warranty",
            "Powerful 12-amp motor; extra-wide cleaning path with side brushes to reach more dirt",
            "Bagless technology extends suction power for more thorough cleaning",
            "HEPA media filter captures 99.9 percent of dust mites, pollens, and ragweed",
            "On-board tools include TurboBrush for pet hair, stairs"
        ]
    },
    {
        "ID": "B001D1YO84.html",
        "NAME": "Readivac 36827 Room Zoom Stick Vacuum Cleaner, Blue - Corded",
        "CATEGORY": [
            "Home & Kitchen",
            "Vacuums & Floor Care",
            "Vacuums",
            "Stick Vacuums & Electric Brooms"
        ],
        "DESCRIPTION": [
            "Light weight only 3.2 pound",
            "Room Zoom folds in half for convenient storage and portability",
            "Extra long 25-foot cord",
            "Bagless design and resuable washable filter",
            "Dual function brush head is ideal for carpets and hard surfaces. Foot pedel on the brush head quickly adjusts height of suction"
        ]
    },
    {
        "ID": "B0009SU03U.html",
        "NAME": "Bissell 3596 CleanView Revolution Deluxe Upright Bagless Vacuum",
        "CATEGORY": [
            "Home & Kitchen",
            "Vacuums & Floor Care",
            "Vacuums",
            "Upright Vacuums"
        ],
        "DESCRIPTION": [
            "Bagless Revolution System-Extends suction power for better cleaning performance",
            "Maximum Cleaning Power - powerful suction with a 12 amp motor",
            "15\"L X 12.5\"W X 44\"H, 17 lbs.",
            "Electronic Dirt Sensor lets you know when the carpet is clean",
            "Clean Filter Indicator-will monitor the air flow and let you know when it's time to clean your filters"
        ]
    }
]